wccontrol.py
wccontrol-2.1.1.dist-info/METADATA
wccontrol-2.1.1.dist-info/WHEEL
wccontrol-2.1.1.dist-info/entry_points.txt
wccontrol-2.1.1.dist-info/top_level.txt
wccontrol-2.1.1.dist-info/RECORD
