Metadata-Version: 2.4
Name: wccontrol
Version: 2.1.1
Summary: Python module/program to control Watts Clever switch
Author-email: Mark Blakeney <mark.blakeney@bullet-systems.net>
License-Expression: GPL-3.0-or-later
Project-URL: Homepage, https://github.com/bulletmark/wccontrol
Keywords: rpi,pi
Classifier: Programming Language :: Python :: 3
Requires-Python: >=3.6
Requires-Dist: rpi.gpio
